{
  "title": "Windows basics: Ctrl C/V/X/Z + Shift+Z Redo + Home/End + Find/Replace + Select All + Save + Brackets",
  "rules": [
    {
      "description": "Fix Swiss keyboard: ยง and < swap (inkl. Shift)",
      "manipulators": [
        {
          "type": "basic",
          "from": { "key_code": "grave_accent_and_tilde", "modifiers": { "mandatory": ["shift"] } },
          "to": [{ "key_code": "non_us_backslash", "modifiers": ["shift"] }]
        },
        {
          "type": "basic",
          "from": { "key_code": "non_us_backslash", "modifiers": { "mandatory": ["shift"] } },
          "to": [{ "key_code": "grave_accent_and_tilde", "modifiers": ["shift"] }]
        },
        {
          "type": "basic",
          "from": { "key_code": "grave_accent_and_tilde" },
          "to": [{ "key_code": "non_us_backslash" }]
        },
        {
          "type": "basic",
          "from": { "key_code": "non_us_backslash" },
          "to": [{ "key_code": "grave_accent_and_tilde" }]
        }
      ]
    },
    {
      "description": "AltGr+keys -> Windows DE-CH bracket/pipe/backslash/hash positions",
      "manipulators": [
        {
          "type": "basic",
          "from": { "key_code": "open_bracket", "modifiers": { "mandatory": ["right_command"] } },
          "to": [{ "key_code": "5", "modifiers": ["option"] }]
        },
        {
          "type": "basic",
          "from": { "key_code": "close_bracket", "modifiers": { "mandatory": ["right_command"] } },
          "to": [{ "key_code": "6", "modifiers": ["option"] }]
        },
        {
          "type": "basic",
          "from": { "key_code": "quote", "modifiers": { "mandatory": ["right_command"] } },
          "to": [{ "key_code": "8", "modifiers": ["option"] }]
        },
        {
          "type": "basic",
          "from": { "key_code": "backslash", "modifiers": { "mandatory": ["right_command"] } },
          "to": [{ "key_code": "9", "modifiers": ["option"] }]
        },
        {
          "type": "basic",
          "from": { "key_code": "7", "modifiers": { "mandatory": ["right_command"] } },
          "to": [{ "key_code": "7", "modifiers": ["option"] }]
        },
        {
          "type": "basic",
          "from": { "key_code": "grave_accent_and_tilde", "modifiers": { "mandatory": ["right_command"] } },
          "to": [{ "key_code": "7", "modifiers": ["option", "shift"] }]
        },
        {
          "type": "basic",
          "from": { "key_code": "3", "modifiers": { "mandatory": ["right_command"] } },
          "to": [{ "key_code": "3", "modifiers": ["option"] }]
        }
      ]
    },
    {
      "description": "Ctrl+C/V/X -> Cmd+C/V/X (except terminals)",
      "manipulators": [
        {
          "type": "basic",
          "from": { "key_code": "c", "modifiers": { "mandatory": ["control"] } },
          "to": [{ "key_code": "c", "modifiers": ["command"] }],
          "conditions": [{ "type": "frontmost_application_unless", "bundle_identifiers": ["^com\\.apple\\.Terminal$", "^com\\.googlecode\\.iterm2$", "^co\\.zeit\\.hyper$", "^com\\.github\\.wez\\.wezterm$"] }]
        },
        {
          "type": "basic",
          "from": { "key_code": "v", "modifiers": { "mandatory": ["control"] } },
          "to": [{ "key_code": "v", "modifiers": ["command"] }],
          "conditions": [{ "type": "frontmost_application_unless", "bundle_identifiers": ["^com\\.apple\\.Terminal$", "^com\\.googlecode\\.iterm2$", "^co\\.zeit\\.hyper$", "^com\\.github\\.wez\\.wezterm$"] }]
        },
        {
          "type": "basic",
          "from": { "key_code": "x", "modifiers": { "mandatory": ["control"] } },
          "to": [{ "key_code": "x", "modifiers": ["command"] }],
          "conditions": [{ "type": "frontmost_application_unless", "bundle_identifiers": ["^com\\.apple\\.Terminal$", "^com\\.googlecode\\.iterm2$", "^co\\.zeit\\.hyper$", "^com\\.github\\.wez\\.wezterm$"] }]
        }
      ]
    },
    {
      "description": "Ctrl+Z -> Cmd+Z (Undo), Ctrl+Shift+Z -> Cmd+Shift+Z (Redo) (except terminals)",
      "manipulators": [
        {
          "type": "basic",
          "from": { "key_code": "y", "modifiers": { "mandatory": ["control", "shift"] } },
          "to": [{ "key_code": "y", "modifiers": ["command", "shift"] }],
          "conditions": [{ "type": "frontmost_application_unless", "bundle_identifiers": ["^com\\.apple\\.Terminal$", "^com\\.googlecode\\.iterm2$", "^co\\.zeit\\.hyper$", "^com\\.github\\.wez\\.wezterm$"] }]
        },
        {
          "type": "basic",
          "from": { "key_code": "y", "modifiers": { "mandatory": ["control"] } },
          "to": [{ "key_code": "y", "modifiers": ["command"] }],
          "conditions": [{ "type": "frontmost_application_unless", "bundle_identifiers": ["^com\\.apple\\.Terminal$", "^com\\.googlecode\\.iterm2$", "^co\\.zeit\\.hyper$", "^com\\.github\\.wez\\.wezterm$"] }]
        }
      ]
    },
    {
      "description": "Ctrl+F -> Cmd+F (Find), Ctrl+H -> Opt+Cmd+F (Find & Replace) (except terminals)",
      "manipulators": [
        {
          "type": "basic",
          "from": { "key_code": "f", "modifiers": { "mandatory": ["control"] } },
          "to": [{ "key_code": "f", "modifiers": ["command"] }],
          "conditions": [{ "type": "frontmost_application_unless", "bundle_identifiers": ["^com\\.apple\\.Terminal$", "^com\\.googlecode\\.iterm2$", "^co\\.zeit\\.hyper$", "^com\\.github\\.wez\\.wezterm$"] }]
        },
        {
          "type": "basic",
          "from": { "key_code": "h", "modifiers": { "mandatory": ["control"] } },
          "to": [{ "key_code": "f", "modifiers": ["command", "option"] }],
          "conditions": [{ "type": "frontmost_application_unless", "bundle_identifiers": ["^com\\.apple\\.Terminal$", "^com\\.googlecode\\.iterm2$", "^co\\.zeit\\.hyper$", "^com\\.github\\.wez\\.wezterm$"] }]
        }
      ]
    },
    {
      "description": "Ctrl+A -> Cmd+A (Select All) (except terminals)",
      "manipulators": [
        {
          "type": "basic",
          "from": { "key_code": "a", "modifiers": { "mandatory": ["control"] } },
          "to": [{ "key_code": "a", "modifiers": ["command"] }],
          "conditions": [{ "type": "frontmost_application_unless", "bundle_identifiers": ["^com\\.apple\\.Terminal$", "^com\\.googlecode\\.iterm2$", "^co\\.zeit\\.hyper$", "^com\\.github\\.wez\\.wezterm$"] }]
        }
      ]
    },
    {
      "description": "Ctrl+S -> Cmd+S (Save) (except terminals)",
      "manipulators": [
        {
          "type": "basic",
          "from": { "key_code": "s", "modifiers": { "mandatory": ["control"] } },
          "to": [{ "key_code": "s", "modifiers": ["command"] }],
          "conditions": [{ "type": "frontmost_application_unless", "bundle_identifiers": ["^com\\.apple\\.Terminal$", "^com\\.googlecode\\.iterm2$", "^co\\.zeit\\.hyper$", "^com\\.github\\.wez\\.wezterm$"] }]
        }
      ]
    },
    {
      "description": "Home/End -> Cmd+Left/Right",
      "manipulators": [
        {
          "type": "basic",
          "from": { "key_code": "home" },
          "to": [{ "key_code": "left_arrow", "modifiers": ["command"] }]
        },
        {
          "type": "basic",
          "from": { "key_code": "end" },
          "to": [{ "key_code": "right_arrow", "modifiers": ["command"] }]
        }
      ]
    }
  ]
}
